shield/__init__.py
shield/cli.py
shield/core.py
shield/commands/__init__.py
shield/commands/config.py
shield/commands/logs.py
shield/commands/monitor.py
shield/commands/os_plugins.py
shield/commands/restart.py
shield/commands/services.py
shield/commands/setup.py
shield/commands/status.py
shield/commands/stop.py
shield/commands/systemd.py
shield/commands/test.py
shield/commands/uninstall.py
shield/services/__init__.py
shield/services/ssh_bruteforce.py
shield/services/sudo_abuse.py
tests/__init__.py
tests/test_ssh_bruteforce.py
tests/test_sudo_abuse.py
minaki_shield-1.1.3.dist-info/METADATA
minaki_shield-1.1.3.dist-info/WHEEL
minaki_shield-1.1.3.dist-info/entry_points.txt
minaki_shield-1.1.3.dist-info/top_level.txt
minaki_shield-1.1.3.dist-info/RECORD
