Metadata-Version: 2.4
Name: minaki-shield
Version: 1.1.3
Summary: Modular Linux intrusion detection CLI by MinakiLabs
Author: Andrew Polykandriotis
Classifier: Programming Language :: Python :: 3
Classifier: License :: OSI Approved :: MIT License
Classifier: Operating System :: POSIX :: Linux
Classifier: Intended Audience :: System Administrators
Classifier: Topic :: Security
Requires-Dist: click
Requires-Dist: psutil
Dynamic: author
Dynamic: classifier
Dynamic: description
Dynamic: description-content-type
Dynamic: requires-dist
Dynamic: summary
